top/Shift4.v
module Shift4 #(
    parameter size = 4
) (
    input                   clk,
    input                   areset,  // async active-high reset to zero
    input                   load,
    input                   ena,
    input      [size - 1:0] data,
    output reg [size - 1:0] q
);

  always @(posedge clk or posedge areset) begin
    casez ({
      areset, load, ena
    })
      3'b1??:  q <= 4'b0000;
      3'b01?:  q <= data;
      3'b001:  q <= q >> 1;
      default: q <= q;
    endcase
  end

endmodule

testbench/shift4_tb.v
`include "../top/Shift4.v"

module Shift4_tb;

  // Parameters
  localparam size = 4;

  // Ports
  reg clk = 0;
  reg areset = 0;
  reg load = 0;
  reg ena = 0;
  reg [size - 1:0] data;
  wire [size - 1:0] q;

  Shift4 #(
      .size(size)
  ) Shift4_dut (
      .clk(clk),
      .areset(areset),
      .load(load),
      .ena(ena),
      .data(data),
      .q(q)
  );

  initial begin
    $dumpfile("shift_wave.vcd");
    $dumpvars;
    begin
      #10 areset = 1;
      #5 areset = 0;
      #5 data = 4'b1111;
      #5 ena = 1;
      #5 load = 1;
      #10 load = 0;
      #100;
      $finish;
    end
  end

  always #5 clk = !clk;

endmodule

testbench/shift_wave.vcd
$date
	Sat Apr 22 01:15:58 2023
$end
$version
	Icarus Verilog
$end
$timescale
	1s
$end
$scope module Shift4_tb $end
$var wire 4 ! q [3:0] $end
$var reg 1 " areset $end
$var reg 1 # clk $end
$var reg 4 $ data [3:0] $end
$var reg 1 % ena $end
$var reg 1 & load $end
$scope module Shift4_dut $end
$var wire 1 " areset $end
$var wire 1 # clk $end
$var wire 4 ' data [3:0] $end
$var wire 1 % ena $end
$var wire 1 & load $end
$var reg 4 ( q [3:0] $end
$upscope $end
$upscope $end
$enddefinitions $end
#0
$dumpvars
bx (
bx '
0&
0%
bx $
0#
0"
bx !
$end
#5
1#
#10
b0 !
b0 (
0#
1"
#15
1#
0"
#20
0#
b1111 $
b1111 '
#25
1#
1%
#30
0#
1&
#35
b1111 !
b1111 (
1#
#40
0#
0&
#45
b111 !
b111 (
1#
#50
0#
#55
b11 !
b11 (
1#
#60
0#
#65
b1 !
b1 (
1#
#70
0#
#75
b0 !
b0 (
1#
