top/Shift4.v
module Shift4 #(
    parameter size = 4
) (
    input                    clk,
    input                    areset,  // async active-high reset to zero
    input                    load,
    input                    ena,
    input       [size - 1:0] data,
    output wire [size - 1:0] q
);

  reg [size - 1:0] q_drain = 4'b0000;

  always @(posedge clk or posedge areset) begin : _FSM
    if (areset) begin
      q_drain <= 4'b0000;
    end else begin
      if (load) begin
        q_drain <= data;
      end else if (ena) begin
        q_drain <= q >> 1;
      end else begin
        q_drain <= q;
      end
    end
  end

  assign q = q_drain;

endmodule

testbench/shift4_tb.v
`include "../top/Shift4.v"

module Shift4_tb;

  // Parameters
  localparam size = 4;

  // Ports
  reg               clk;
  reg               areset;
  reg               load;
  reg               ena;
  reg  [size - 1:0] data;
  wire [size - 1:0] q;

  Shift4 #(
      .size(size)
  ) Shift4_dut (
      .clk(clk),
      .areset(areset),
      .load(load),
      .ena(ena),
      .data(data),
      .q(q)
  );


  initial begin
    $dumpfile("shift_wave.vcd");
    $dumpvars;
    begin
      clk = 1;
      areset = 0;
      load = 1;
      ena = 0;
      data = 4'b1111;
    end
    begin
      #9 load = 0;
      data = 'x;
      #10 ena = 1;
      #20 ena = 0;
      #55 areset = 1;
      #15 areset = 0;
      #50;
      $finish;
    end
  end

  always begin
    #5 clk = !clk;
  end

endmodule

testbench/shift_wave.vcd
$date
	Sat Apr 22 02:59:00 2023
$end
$version
	Icarus Verilog
$end
$timescale
	1s
$end
$scope module Shift4_tb $end
$var wire 4 ! q [3:0] $end
$var reg 1 " areset $end
$var reg 1 # clk $end
$var reg 4 $ data [3:0] $end
$var reg 1 % ena $end
$var reg 1 & load $end
$scope module Shift4_dut $end
$var wire 1 " areset $end
$var wire 1 # clk $end
$var wire 4 ' data [3:0] $end
$var wire 1 % ena $end
$var wire 1 & load $end
$var wire 4 ( q [3:0] $end
$var reg 4 ) q_drain [3:0] $end
$scope begin _FSM $end
$upscope $end
$upscope $end
$upscope $end
$enddefinitions $end
#0
$dumpvars
b0 )
b0 (
bx '
x&
x%
bx $
x#
x"
b0 !
$end
#1
b1111 !
b1111 (
b1111 )
b1111 $
b1111 '
0%
1&
0"
1#
#5
0#
#10
1#
bx $
bx '
0&
#15
0#
#20
b111 !
b111 (
b111 )
1#
1%
#25
0#
#30
b11 !
b11 (
b11 )
1#
#35
0#
#40
1#
0%
#45
0#
#50
1#
#55
0#
#60
1#
#65
0#
#70
1#
#75
0#
#80
1#
#85
0#
#90
1#
#95
b0 !
b0 (
b0 )
0#
1"
#100
1#
#105
0#
#110
1#
0"
